build/lib/build/lib/build/lib/build/lib/build/lib/build/lib/jafgen/__init__.py
build/lib/build/lib/build/lib/build/lib/build/lib/build/lib/jafgen/cli.py
build/lib/build/lib/build/lib/build/lib/build/lib/build/lib/jafgen/curves.py
build/lib/build/lib/build/lib/build/lib/build/lib/build/lib/jafgen/simulation.py
build/lib/build/lib/build/lib/build/lib/build/lib/build/lib/jafgen/time.py
build/lib/build/lib/build/lib/build/lib/build/lib/build/lib/jafgen/customers/__init__.py
build/lib/build/lib/build/lib/build/lib/build/lib/build/lib/jafgen/customers/customers.py
build/lib/build/lib/build/lib/build/lib/build/lib/build/lib/jafgen/customers/order.py
build/lib/build/lib/build/lib/build/lib/build/lib/build/lib/jafgen/customers/tweet.py
build/lib/build/lib/build/lib/build/lib/build/lib/build/lib/jafgen/stores/__init__.py
build/lib/build/lib/build/lib/build/lib/build/lib/build/lib/jafgen/stores/inventory.py
build/lib/build/lib/build/lib/build/lib/build/lib/build/lib/jafgen/stores/item.py
build/lib/build/lib/build/lib/build/lib/build/lib/build/lib/jafgen/stores/market.py
build/lib/build/lib/build/lib/build/lib/build/lib/build/lib/jafgen/stores/stock.py
build/lib/build/lib/build/lib/build/lib/build/lib/build/lib/jafgen/stores/store.py
build/lib/build/lib/build/lib/build/lib/build/lib/build/lib/jafgen/stores/supply.py
build/lib/build/lib/build/lib/build/lib/build/lib/jafgen/__init__.py
build/lib/build/lib/build/lib/build/lib/build/lib/jafgen/cli.py
build/lib/build/lib/build/lib/build/lib/build/lib/jafgen/curves.py
build/lib/build/lib/build/lib/build/lib/build/lib/jafgen/simulation.py
build/lib/build/lib/build/lib/build/lib/build/lib/jafgen/time.py
build/lib/build/lib/build/lib/build/lib/build/lib/jafgen/customers/__init__.py
build/lib/build/lib/build/lib/build/lib/build/lib/jafgen/customers/customers.py
build/lib/build/lib/build/lib/build/lib/build/lib/jafgen/customers/order.py
build/lib/build/lib/build/lib/build/lib/build/lib/jafgen/customers/tweet.py
jafkafegen-0.4.19.dist-info/licenses/LICENSE
jafkafegen-0.4.19.dist-info/METADATA
jafkafegen-0.4.19.dist-info/WHEEL
jafkafegen-0.4.19.dist-info/entry_points.txt
jafkafegen-0.4.19.dist-info/top_level.txt
jafkafegen-0.4.19.dist-info/RECORD
