Metadata-Version: 2.4
Name: jafkafegen
Version: 0.4.19
Summary: A fork of the dbtlabs Jaffle Shop generator, for baking realtime jaffles on kafka.
Author-email: Jens Köster <pypi@jensbox.se>
License:                                  Apache License
License-File: LICENSE
Requires-Dist: numpy
Requires-Dist: Faker
Requires-Dist: typer
Provides-Extra: dev
Requires-Dist: ruff; extra == "dev"
Requires-Dist: pytest; extra == "dev"
Dynamic: license-file
